{
  "$schema": "https://schema.tauri.app/config/2",
  "productName": "Macsplorer",
  "version": "0.1.2",
  "identifier": "com.macsplorer.app",
  "build": {
    "frontendDist": "../src"
  },
  "app": {
    "withGlobalTauri": true,
    "windows": [
      {
        "title": "Macsplorer",
        "width": 1280,
        "height": 820,
        "minWidth": 920,
        "minHeight": 600,
        "decorations": false,
        "transparent": true,
        "resizable": true,
        "center": true
      }
    ],
    "security": {
      "csp": "default-src 'self'; script-src 'self'; style-src 'self' 'unsafe-inline'; img-src 'self' asset: https://asset.localhost data: blob:; font-src 'self' data:; connect-src 'self' ipc: https://ipc.localhost https://api.github.com https://github.com https://*.githubusercontent.com; media-src 'self' asset: https://asset.localhost; object-src 'none'; frame-ancestors 'none'; base-uri 'self'",
      "assetProtocol": {
        "enable": true,
        "scope": [
          "**"
        ]
      }
    }
  },
  "bundle": {
    "active": true,
    "targets": [
      "nsis"
    ],
    "icon": [
      "icons/32x32.png",
      "icons/128x128.png",
      "icons/128x128@2x.png",
      "icons/icon.ico"
    ],
    "windows": {
      "nsis": {
        "installMode": "currentUser"
      }
    }
  }
}
